pysnurr/__init__.py
pysnurr/spinner.py
pysnurr/terminal.py
pysnurr-0.6.0.dist-info/METADATA
pysnurr-0.6.0.dist-info/WHEEL
pysnurr-0.6.0.dist-info/licenses/LICENSE
pysnurr-0.6.0.dist-info/RECORD
