Metadata-Version: 2.4
Name: pysnurr
Version: 0.6.0
Summary: A beautiful terminal spinner library for Python
Project-URL: Homepage, https://github.com/dewe/pysnurr
Project-URL: Repository, https://github.com/dewe/pysnurr
Project-URL: Issues, https://github.com/dewe/pysnurr/issues
Author: dewe
License-Expression: MIT
License-File: LICENSE
Keywords: cli,loading,progress,spinner,terminal
Classifier: Development Status :: 4 - Beta
Classifier: Environment :: Console
Classifier: Intended Audience :: Developers
Classifier: License :: OSI Approved :: MIT License
Classifier: Operating System :: OS Independent
Classifier: Programming Language :: Python :: 3
Classifier: Programming Language :: Python :: 3.10
Classifier: Programming Language :: Python :: 3.11
Classifier: Programming Language :: Python :: 3.12
Classifier: Topic :: Software Development :: Libraries :: Python Modules
Classifier: Topic :: Software Development :: User Interfaces
Requires-Python: >=3.10
Requires-Dist: regex>=2024.11.6
Requires-Dist: wcwidth>=0.2.13
Provides-Extra: test
Requires-Dist: black>=24.1.0; extra == 'test'
Requires-Dist: mypy>=1.8.0; extra == 'test'
Requires-Dist: pytest>=7.0.0; extra == 'test'
Requires-Dist: ruff>=0.2.0; extra == 'test'
Requires-Dist: types-regex>=2024.11.6; extra == 'test'
